bamboorules/__init__.py
bamboorules/engine.py
bamboorules-0.0.1.dev11.dist-info/AUTHORS
bamboorules-0.0.1.dev11.dist-info/LICENSE
bamboorules-0.0.1.dev11.dist-info/METADATA
bamboorules-0.0.1.dev11.dist-info/WHEEL
bamboorules-0.0.1.dev11.dist-info/pbr.json
bamboorules-0.0.1.dev11.dist-info/top_level.txt
bamboorules-0.0.1.dev11.dist-info/RECORD
